muffin_prometheus/__init__.py
muffin_prometheus/py.typed
muffin_prometheus-1.4.1.dist-info/METADATA
muffin_prometheus-1.4.1.dist-info/WHEEL
muffin_prometheus-1.4.1.dist-info/RECORD
