Metadata-Version: 2.1
Name: muffin-prometheus
Version: 1.4.1
Summary: Prometheus metrics exporter for Muffin framework
Home-page: https://github.com/klen/muffin-prometheus
License: MIT
Keywords: prometheus-exporter,muffin,asyncio,trio,curio
Author: Kirill Klenov
Author-email: horneds@gmail.com
Requires-Python: >=3.9,<4.0
Classifier: Development Status :: 5 - Production/Stable
Classifier: Framework :: AsyncIO
Classifier: Framework :: Trio
Classifier: Intended Audience :: Developers
Classifier: License :: OSI Approved :: MIT License
Classifier: Programming Language :: Python
Classifier: Programming Language :: Python :: 3
Classifier: Programming Language :: Python :: 3.9
Classifier: Programming Language :: Python :: 3.10
Classifier: Programming Language :: Python :: 3.11
Classifier: Programming Language :: Python :: 3.12
Classifier: Topic :: Internet :: WWW/HTTP
Requires-Dist: asgi-prometheus (>=1.1.2,<2.0.0)
Requires-Dist: muffin (>=0,<1)
Project-URL: Repository, https://github.com/klen/muffin-prometheus
